rocrate_action_recorder/__about__.py
rocrate_action_recorder/__init__.py
rocrate_action_recorder/core.py
rocrate_action_recorder/py.typed
rocrate_action_recorder/adapters/__init__.py
rocrate_action_recorder/adapters/argparse.py
rocrate_action_recorder-0.1.0.dist-info/METADATA
rocrate_action_recorder-0.1.0.dist-info/WHEEL
rocrate_action_recorder-0.1.0.dist-info/licenses/LICENSE
rocrate_action_recorder-0.1.0.dist-info/RECORD
