Metadata-Version: 2.4
Name: rocrate-action-recorder
Version: 0.1.0
Summary: Record calls of Python CLI commands into a Research Object Crate
Project-URL: Homepage, https://github.com/i-VRESSE/rocrate-action-recorder
Project-URL: Repository, https://github.com/i-VRESSE/rocrate-action-recorder
Project-URL: Issues, https://github.com/i-VRESSE/rocrate-action-recorder/issues
Project-URL: Documentation, https://rocrate-action-recorder.readthedocs.io/
Author-email: Stefan Verhoeven <stefan.verhoeven@gmail.com>
License-File: LICENSE
Classifier: Development Status :: 4 - Beta
Classifier: Intended Audience :: Developers
Classifier: License :: OSI Approved :: Apache Software License
Classifier: Programming Language :: Python :: 3
Classifier: Programming Language :: Python :: 3.13
Classifier: Programming Language :: Python :: 3.14
Classifier: Topic :: Software Development :: Libraries
Requires-Python: >=3.13
Requires-Dist: rocrate>=0.14.2
